LICENSE
MANIFEST.in
README.md
requirements.txt
setup.cfg
setup.py
gdspy/__init__.py
gdspy/clipper.cpp
gdspy/clipper.hpp
gdspy/curve.py
gdspy/gdsiiformat.py
gdspy/hobby.py
gdspy/label.py
gdspy/library.py
gdspy/operation.py
gdspy/path.py
gdspy/polygon.py
gdspy/viewer.py
gdspy.egg-info/PKG-INFO
gdspy.egg-info/SOURCES.txt
gdspy.egg-info/dependency_links.txt
gdspy.egg-info/not-zip-safe
gdspy.egg-info/requires.txt
gdspy.egg-info/top_level.txt
gdspy/data/00.xbm
gdspy/data/01.xbm
gdspy/data/02.xbm
gdspy/data/03.xbm
gdspy/data/04.xbm
gdspy/data/05.xbm
gdspy/data/06.xbm
gdspy/data/07.xbm
gdspy/data/08.xbm
gdspy/data/09.xbm
gdspy/data/down.xbm
gdspy/data/outline.xbm
gdspy/data/up.xbm