Metadata-Version: 2.1
Name: gdspy
Version: 1.6.9
Summary: Python module for creating/importing/merging GDSII files.
Home-page: https://github.com/heitzmann/gdspy
Author: Lucas Heitzmann Gabrielli
Author-email: heitzmann@gmail.com
License: Boost Software License v1.0
Keywords: GDSII CAD layout
Platform: OS Independent
Classifier: Development Status :: 5 - Production/Stable
Classifier: Environment :: Console
Classifier: Intended Audience :: Developers
Classifier: Intended Audience :: Manufacturing
Classifier: Intended Audience :: Science/Research
Classifier: License :: OSI Approved :: Boost Software License 1.0 (BSL-1.0)
Classifier: Operating System :: OS Independent
Classifier: Programming Language :: C
Classifier: Programming Language :: C++
Classifier: Programming Language :: Python
Classifier: Programming Language :: Python :: Implementation :: CPython
Classifier: Topic :: Scientific/Engineering :: Electronic Design Automation (EDA)
Provides: gdspy
License-File: LICENSE
